facerecog/__init__.py
facerecog/face-detection-in-pyqt.py
facerecog/haarcascade_frontalface_default.xml
facerecog-0.0.1.dist-info/DESCRIPTION.rst
facerecog-0.0.1.dist-info/METADATA
facerecog-0.0.1.dist-info/RECORD
facerecog-0.0.1.dist-info/WHEEL
facerecog-0.0.1.dist-info/metadata.json
facerecog-0.0.1.dist-info/top_level.txt
